DatabaseConnectionUtility/AmazonRedshift.py
DatabaseConnectionUtility/Dremio.py
DatabaseConnectionUtility/ExcelFile.py
DatabaseConnectionUtility/FileURL.py
DatabaseConnectionUtility/GoogleBigQuery.py
DatabaseConnectionUtility/InMemory.py
DatabaseConnectionUtility/MSSQLServer.py
DatabaseConnectionUtility/MySql.py
DatabaseConnectionUtility/Oracle.py
DatabaseConnectionUtility/Postgress.py
DatabaseConnectionUtility/ProteusVision.py
DatabaseConnectionUtility/RestAPI.py
DatabaseConnectionUtility/SAPHANA.py
DatabaseConnectionUtility/SQLServer.py
DatabaseConnectionUtility/SnowFlake.py
DatabaseConnectionUtility/Tally.py
DatabaseConnectionUtility/TestDBConnection.py
DatabaseConnectionUtility/__init__.py
databaseconnectionutility-0.0.36.dist-info/LICENCE.txt
databaseconnectionutility-0.0.36.dist-info/METADATA
databaseconnectionutility-0.0.36.dist-info/WHEEL
databaseconnectionutility-0.0.36.dist-info/top_level.txt
databaseconnectionutility-0.0.36.dist-info/RECORD
